Workbook

Sheet Show Dates
A1: Title | B1: Type | C1: Category | D1: Event Date(s) | E1: actors/tech
A2: Finding Nemo | B2: Show | C2: Theater | D2: 07/24-25/2026 | E2: 5pm,8pm and 10am | F2: Cash box, square, ludus, table, Ticket box,
A4: Back to School Event | B4: Event | C4: General | D4: 46253 | F4: Welcome Flyers
A6: Ice Cream Social | B6: Show | C6: General | D6: 46254 | F6: Welcome Flyers Face Paint? Pay a Cone Forward?
A8: Heros vs Villans | B8: Show | C8: Theater | D8: 46289
A10: NCTS | B10: Event | C10: General | D10: 10/29-31/2026 | F10: *~$50Fees for Tshirts and Picnic type lunchbox, Festival Entrance,
A12: Fall Concert for Chorus | B12: Show | C12: Choir | F12: *Bake Sale with Coffee
A14: The Great Gatsby | B14: Show | C14: Theater | D14: 09/12/2026 Auditions | E14: 20/15-30 | F14: Dues $125 for non volunteers, $100 for actors, $75 for Tech
D15: 10/7-8/2026 Call backs
D16: 11/09-11/2026 Tech Week
D17: 11/12-14/2026 Show
A19: Southern Christmas Show* | B19: Show | C19: Choir | D19: 11/11-22/2026
A21: Biltmore performance* | B21: Show | C21: Choir | D21: 46357
A23: Revue in Reverse * | B23: Theater | C23: Theater | D23: 46036 | F23: *Dues for Tshirts, lite concessions
D24: or 01/7/2026 *Check date
A26: Alice by Heart | B26: Theater | C26: Theater | D26: 12/1-2/2026 Auditions | E26: 25/15-30 | F26: Dues $125 for non volunteers, $100 for actors, $75 for Tech
D27: 12/10-11/2026 Show
A29: Holiday Bazar | B29: Event | C29: General | D29: 12/5-6/2026
A31: Italian Dinner* | B31: Choir | C31: Choir | D31: 46082
A33: Dreams vs Nightmare | B33: Show | C33: Theater | D33: 46106 | F33: voting option this year
A35: Hunchback of Notre Dame | B35: Show | C35: Theater | D35: 10/1/2026 Informational meeting
D36: 10/9/2026 Auditions | E36: 30-35/15-30
D37: 04/4-7/2026 Tech Week
D38: 04/08-10 & 15-17/2026 Show
A40: Theatre I & II Production | B40: Show | C40: Theater | D40: 46153
A42: Senior Showcase | B42: Show | C42: Theater | D42: 46157
A44: Carowinds | B44: Shows | C44: Choir | D44: 46143
E46: *Recycle Programs? May need less

Sheet Sheet7
A2: Publix | B2: Box Sandwiches | C2: ~12.00/box
A3: Chic-fil-A | B3: Chicken Sandwich | C3: 125/25 Sandwiches
A4: Pizza Hut | B4: personal pan pizza | C4: 4.79/pizza
A5: Jersey Mikes | B5: Turkey Provolone | C5: 7.16/Sandwich | D5: 85.95/12

Sheet Great Gatsby
A1: Merchandise
A2: Custom Cards | B2: ~$2/pack (12)
A3: Paper Fans | B3: ~$1/fan (12)
A4: Art Deco Paintings | B4: ~$1.50/canvas | D4: Audition Dates
A5: Pearls | B5: ~$0.50/necklace | D5: Play dates
A6: Garters | B6: ~$1/garter (12) | D6: Tech Week
A9: Food
A10: Cracker Jacks | B10: ~0.30/bag
A11: Water | B11: ~0.20/bottle
A12: Coffee
A13: Green Lantern Drink | B13: ~0.25/ice cube
A14: Shirley Temples
A15: Salt Water Taffy
A16: Pizza | B16: ~$2/slice
A17: Soft Pretzels | B17: ~$1/Pretzel
A18: Popcorn
A19: fudge
A20: Candy Stix | B20: ~0.30/stick
A21: hoochi coochie cups
A22: carmel cremes
A24: Decor
A25: Black and Gold Tableclothes
A26: Vintage Candy Jars
A27: Gold Trays
A28: Deco Art Signs | B28: ~$1.52/poster (pk 6)

Sheet Ice Cream Social
A2: Have flyer ready to handout
A3: Ice Cream playlist Speakers? | D3: Aug 20th, Mineral Springs 12-4
A4: Bags game?
A5: Bocce?
A6: Sidewalk Chalk?
A7: Character Dress up?
A8: Face painting?
A9: Balloon animals?
A10: Bubble Machine?
A11: Get reminders out especially to elementary and middle school
A12: Posters to have outside ice cream shop?
A14: Megaphone=Ice Cream Jokes

Sheet Alice by Heart
A1: Merchandise
A2: Playing Cards
A3: Dog tags
A8: Food
A9: Butterfly tea lemonade
A10: Boba tea
A11: Finger Sandwiches
A12: Eat Me Cookies
A13: Drink Me Drink
A14: Red Candies
A15: Carrot Cake/Red Velvet Cupcakes/Bundt Cakes
A16: White Cheddar Popcorn
... A26: Black light/Laundry detergent

Sheet Hunchback
A1: Merchandise
A2: King of Fools Crown | B2: felt?
A3: Esmerelda's Potion
A4: stained glass window kits/or already made
A5: Tambourines | B5: ~$1.67/ per instrument
A6: Scarves
A7: mini gargoyoles to paint at home
A8: masquarade?
A13: Food
A14: Water
A15: Coffee

Sheet Misc
A2: Merchandise ideas
A3: Buttons
A4: Stickers
A5: Magnets
A6: Show Posters Signed by Cast
A7: Show Themed cups
A8: Light up items

Sheet Copy of Theater Budget
A1: 2025-26 CHAOS THEATER BUDGET PLAN
A2: Budget Code | B2: Category 1 | C2: Show Name | D2: Category 2 | E2: Projected Expense | F2: Expected Income | G2: Actual Expense | H2: Actual Income | I2: Comments
A3: T1000 | B3: Summer Camp 1 | C3: Finding Nemo | D3: Dues | F3: 2463.75 | G3: =SUM(SUMIFS(GL!$C:$C,GL!$G:$G,CONCATENATE(A3,"*"),GL!$F:$F,"Refund"),SUMIFS(GL!$C:$C,GL!$G:$G,CONCATENATE(A3,"*"),GL!$F:$F,"Expense")) -> #N/A | H3: =SUMIFS(GL!$C:$C,GL!$G:$G,CONCATENATE($A3,"*"),GL!$F:$F,"Income") -> #N/A
A4: T1001 | B4: Summer Camp 1 | C4: Finding Nemo | D4: T-shirts | E4: -344.94 | G4: =SUM(SUMIFS(GL!$C:$C,GL!$G:$G,CONCATENATE(A4,"*"),GL!$F:$F,"Refund"),SUMIFS(GL!$C:$C,GL!$G:$G,CONCATENATE(A4,"*"),GL!$F:$F,"Expense")) -> #N/A | H4: =SUMIFS(GL!$C:$C,GL!$G:$G,CONCATENATE($A4,"*"),GL!$F:$F,"Income") -> #N/A
A5: T1002 | B5: Summer Camp 2 | C5: Finding Nemo | D5: Dues | F5: 5580 | G5: =SUM(SUMIFS(GL!$C:$C,GL!$G:$G,CONCATENATE(A5,"*"),GL!$F:$F,"Refund"),SUMIFS(GL!$C:$C,GL!$G:$G,CONCATENATE(A5,"*"),GL!$F:$F,"Expense")) -> #N/A | H5: =SUMIFS(GL!$C:$C,GL!$G:$G,CONCATENATE($A5,"*"),GL!$F:$F,"Income") -> #N/A
A6: T1003 | B6: Summer Camp 2 | C6: Finding Nemo | D6: T-shirts | E6: -669.55 | G6: =SUM(SUMIFS(GL!$C:$C,GL!$G:$G,CONCATENATE(A6,"*"),GL!$F:$F,"Refund"),SUMIFS(GL!$C:$C,GL!$G:$G,CONCATENATE(A6,"*"),GL!$F:$F,"Expense")) -> #N/A | H6: =SUMIFS(GL!$C:$C,GL!$G:$G,CONCATENATE($A6,"*"),GL!$F:$F,"Income") -> #N/A
A7: T1004 | B7: Summer Camp 1 & 2 | C7: Finding Nemo | D7: Marketing | E7: -59.07 | G7: =SUM(SUMIFS(GL!$C:$C,GL!$G:$G,CONCATENATE(A7,"*"),GL!$F:$F,"Refund"),SUMIFS(GL!$C:$C,GL!$G:$G,CONCATENATE(A7,"*"),GL!$F:$F,"Expense")) -> #N/A | H7: =SUMIFS(GL!$C:$C,GL!$G:$G,CONCATENATE($A7,"*"),GL!$F:$F,"Income") -> #N/A
A8: T1005 | B8: Summer Camp 1 & 2 | C8: Finding Nemo | D8: Concessions / meals | E8: -102.35 | G8: =SUM(SUMIFS(GL!$C:$C,GL!$G:$G,CONCATENATE(A8,"*"),GL!$F:$F,"Refund"),SUMIFS(GL!$C:$C,GL!$G:$G,CONCATENATE(A8,"*"),GL!$F:$F,"Expense")) -> #N/A | H8: =SUMIFS(GL!$C:$C,GL!$G:$G,CONCATENATE($A8,"*"),GL!$F:$F,"Income") -> #N/A
A9: T1006 | B9: Summer Camp 1 & 2 | C9: Finding Nemo | D9: Ticket Sales | F9: 290 | G9: =SUM(SUMIFS(GL!$C:$C,GL!$G:$G,CONCATENATE(A9,"*"),GL!$F:$F,"Refund"),SUMIFS(GL!$C:$C,GL!$G:$G,CONCATENATE(A9,"*"),GL!$F:$F,"Expense")) -> #N/A | H9: =SUMIFS(GL!$C:$C,GL!$G:$G,CONCATENATE($A9,"*"),GL!$F:$F,"Income") -> #N/A | I9: Tickets for student performance X 10/ticket
A10: T1007 | B10: Summer Camp 1 & 2 | C10: Finding Nemo | D10: Licensing | E10: -1235 | G10: =SUM(SUMIFS(GL!$C:$C,GL!$G:$G,CONCATENATE(A10,"*"),GL!$F:$F,"Refund"),SUMIFS(GL!$C:$C,GL!$G:$G,CONCATENATE(A10,"*"),GL!$F:$F,"Expense")) -> #N/A | H10: =SUMIFS(GL!$C:$C,GL!$G:$G,CONCATENATE($A10,"*"),GL!$F:$F,"Income") -> #N/A
A11: T1008 | B11: Summer Camp 1 & 2 | C11: Finding Nemo | D11: Props, Set, Projections | E11: -354.04 | G11: =SUM(SUMIFS(GL!$C:$C,GL!$G:$G,CONCATENATE(A11,"*"),GL!$F:$F,"Refund"),SUMIFS(GL!$C:$C,GL!$G:$G,CONCATENATE(A11,"*"),GL!$F:$F,"Expense")) -> #N/A | H11: =SUMIFS(GL!$C:$C,GL!$G:$G,CONCATENATE($A11,"*"),GL!$F:$F,"Income") -> #N/A
B12: Totals | C12: =IFERROR(__xludf.DUMMYFUNCTION("AI(""Fill an appropriate value for this cell based on the table context"")"),"=AI(""Fill an appropriate value for this cell based on the table context"")") -> =AI("Fill an appropriate value for this cell based on the table context") | E12: =SUM(E3:E11) -> -2764.95 | F12: =SUM(F3:F11) -> 8333.75 | G12: =SUM(G3:G11) -> #N/A | H12: =SUM(H3:H11) -> #N/A
B13: Net | C13: =IFERROR(__xludf.DUMMYFUNCTION("AI(""Fill an appropriate value for this cell based on the table context"")"),"=AI(""Fill an appropriate value for this cell based on the table context"")") -> =AI("Fill an appropriate value for this cell based on the table context") | F13: =F12+E12 -> 5568.8 | H13: =H12+G12 -> #N/A | I13: Total Net to help cover Student NCTC Dues
C14: =IFERROR(__xludf.DUMMYFUNCTION("AI(""Fill an appropriate value for this cell based on the table context"")"),"=AI(""Fill an appropriate value for this cell based on the table context"")") -> =AI("Fill an appropriate value for this cell based on the table context")
A15: T1009 | B15: NCTC (20 kids) | C15: =IFERROR(__xludf.DUMMYFUNCTION("AI(""Fill an appropriate value for this cell based on the table context"")"),"=AI(""Fill an appropriate value for this cell based on the table context"")") -> =AI("Fill an appropriate value for this cell based on the table context") | D15: Dues | F15: 1000 | G15: =SUM(SUMIFS(GL!$C:$C,GL!$G:$G,CONCATENATE(A15,"*"),GL!$F:$F,"Refund"),SUMIFS(GL!$C:$C,GL!$G:$G,CONCATENATE(A15,"*"),GL!$F:$F,"Expense")) -> #N/A | H15: =SUMIFS(GL!$C:$C,GL!$G:$G,CONCATENATE($A15,"*"),GL!$F:$F,"Income") -> #N/A | I15: Dues: 20 X $50 includes Reg fee, Bus, Substitute, Tshirt, and some food
A16: T1010 | B16: NCTC (20 kids) | C16: =IFERROR(__xludf.DUMMYFUNCTION("AI(""Fill an appropriate value for this cell based on the table context"")"),"=AI(""Fill an appropriate value for this cell based on the table context"")") -> =AI("Fill an appropriate value for this cell based on the table context") | D16: Licensing: $1235 | E16: -150 | G16: =SUM(SUMIFS(GL!$C:$C,GL!$G:$G,CONCATENATE(A16,"*"),GL!$F:$F,"Refund"),SUMIFS(GL!$C:$C,GL!$G:$G,CONCATENATE(A16,"*"),GL!$F:$F,"Expense")) -> #N/A | H16: =SUMIFS(GL!$C:$C,GL!$G:$G,CONCATENATE($A16,"*"),GL!$F:$F,"Income") -> #N/A | I16: *need more more scripts!
A17: T1011 | B17: NCTC (20 kids) | C17: =IFERROR(__xludf.DUMMYFUNCTION("AI(""Fill an appropriate value for this cell based on the table context"")"),"=AI(""Fill an appropriate value for this cell based on the table context"")") -> =AI("Fill an appropriate value for this cell based on the table context") | D17: T-shirts | E17: -360 | F17: 70 | G17: =SUM(SUMIFS(GL!$C:$C,GL!$G:$G,CONCATENATE(A17,"*"),GL!$F:$F,"Refund"),SUMIFS(GL!$C:$C,GL!$G:$G,CONCATENATE(A17,"*"),GL!$F:$F,"Expense")) -> #N/A | H17: =SUMIFS(GL!$C:$C,GL!$G:$G,CONCATENATE($A17,"*"),GL!$F:$F,"Income") -> #N/A | I17: Tee Shirt Costs INCLUDED IN DUES: 20 X $12.00 per shirt
A18: T1012 | B18: NCTC (20 kids) | C18: =IFERROR(__xludf.DUMMYFUNCTION("AI(""Fill an appropriate value for this cell based on the table context"")"),"=AI(""Fill an appropriate value for this cell based on the table context"")") -> =AI("Fill an appropriate value for this cell based on the table context") | D18: Set Build | E18: -240 | G18: =SUM(SUMIFS(GL!$C:$C,GL!$G:$G,CONCATENATE(A18,"*"),GL!$F:$F,"Refund"),SUMIFS(GL!$C:$C,GL!$G:$G,CONCATENATE(A18,"*"),GL!$F:$F,"Expense")) -> #N/A | H18: =SUMIFS(GL!$C:$C,GL!$G:$G,CONCATENATE($A18,"*"),GL!$F:$F,"Income") -> #N/A
A19: T1013 | B19: NCTC (20 kids) | C19: =IFERROR(__xludf.DUMMYFUNCTION("AI(""Fill an appropriate value for this cell based on the table context"")"),"=AI(""Fill an appropriate value for this cell based on the table context"")") -> =AI("Fill an appropriate value for this cell based on the table context") | D19: Props | E19: -325 | G19: =SUM(SUMIFS(GL!$C:$C,GL!$G:$G,CONCATENATE(A19,"*"),GL!$F:$F,"Refund"),SUMIFS(GL!$C:$C,GL!$G:$G,CONCATENATE(A19,"*"),GL!$F:$F,"Expense")) -> #N/A | H19: =SUMIFS(GL!$C:$C,GL!$G:$G,CONCATENATE($A19,"*"),GL!$F:$F,"Income") -> #N/A
A20: T1014 | B20: NCTC (20 kids) | C20: =IFERROR(__xludf.DUMMYFUNCTION("AI(""Fill an appropriate value for this cell based on the table context"")"),"=AI(""Fill an appropriate value for this cell based on the table context"")") -> =AI("Fill an appropriate value for this cell based on the table context") | D20: Costumes | E20: -460 | G20: =SUM(SUMIFS(GL!$C:$C,GL!$G:$G,CONCATENATE(A20,"*"),GL!$F:$F,"Refund"),SUMIFS(GL!$C:$C,GL!$G:$G,CONCATENATE(A20,"*"),GL!$F:$F,"Expense")) -> #N/A | H20: =SUMIFS(GL!$C:$C,GL!$G:$G,CONCATENATE($A20,"*"),GL!$F:$F,"Income") -> #N/A
A21: T1015 | B21: NCTC (20 kids) | C21: =IFERROR(__xludf.DUMMYFUNCTION("AI(""Fill an appropriate value for this cell based on the table context"")"),"=AI(""Fill an appropriate value for this cell based on the table context"")") -> =AI("Fill an appropriate value for this cell based on the table context") | D21: Annual Membership Dues | E21: -400 | G21: =SUM(SUMIFS(GL!$C:$C,GL!$G:$G,CONCATENATE(A21,"*"),GL!$F:$F,"Refund"),SUMIFS(GL!$C:$C,GL!$G:$G,CONCATENATE(A21,"*"),GL!$F:$F,"Expense")) -> #N/A | H21: =SUMIFS(GL!$C:$C,GL!$G:$G,CONCATENATE($A21,"*"),GL!$F:$F,"Income") -> #N/A | I21: NCTC Member dues- $400/yr
A22: T1016 | B22: NCTC (20 kids) | C22: =IFERROR(__xludf.DUMMYFUNCTION("AI(""Fill an appropriate value for this cell based on the table context"")"),"=AI(""Fill an appropriate value for this cell based on the table context"")") -> =AI("Fill an appropriate value for this cell based on the table context") | D22: Festival Admission | E22: 0 | G22: =SUM(SUMIFS(GL!$C:$C,GL!$G:$G,CONCATENATE(A22,"*"),GL!$F:$F,"Refund"),SUMIFS(GL!$C:$C,GL!$G:$G,CONCATENATE(A22,"*"),GL!$F:$F,"Expense")) -> #N/A | H22: =SUMIFS(GL!$C:$C,GL!$G:$G,CONCATENATE($A22,"*"),GL!$F:$F,"Income") -> #N/A
A23: T1017 | B23: NCTC (20 kids) | C23: =IFERROR(__xludf.DUMMYFUNCTION("AI(""Fill an appropriate value for this cell based on the table context"")"),"=AI(""Fill an appropriate value for this cell based on the table context"")") -> =AI("Fill an appropriate value for this cell based on the table context") | D23: Transportation | E23: -250 | G23: =SUM(SUMIFS(GL!$C:$C,GL!$G:$G,CONCATENATE(A23,"*"),GL!$F:$F,"Refund"),SUMIFS(GL!$C:$C,GL!$G:$G,CONCATENATE(A23,"*"),GL!$F:$F,"Expense")) -> #N/A | H23: =SUMIFS(GL!$C:$C,GL!$G:$G,CONCATENATE($A23,"*"),GL!$F:$F,"Income") -> #N/A
A24: T1018 | B24: NCTC (20 kids) | C24: =IFERROR(__xludf.DUMMYFUNCTION("AI(""Fill an appropriate value for this cell based on the table context"")"),"=AI(""Fill an appropriate value for this cell based on the table context"")") -> =AI("Fill an appropriate value for this cell based on the table context") | D24: Meals & Snacks | E24: -1000 | G24: =SUM(SUMIFS(GL!$C:$C,GL!$G:$G,CONCATENATE(A24,"*"),GL!$F:$F,"Refund"),SUMIFS(GL!$C:$C,GL!$G:$G,CONCATENATE(A24,"*"),GL!$F:$F,"Expense")) -> #N/A | H24: =SUMIFS(GL!$C:$C,GL!$G:$G,CONCATENATE($A24,"*"),GL!$F:$F,"Income") -> #N/A | I24: 4 Meals
A25: T1019 | B25: NCTC (20 kids) | C25: =IFERROR(__xludf.DUMMYFUNCTION("AI(""Fill an appropriate value for this cell based on the table context"")"),"=AI(""Fill an appropriate value for this cell based on the table context"")") -> =AI("Fill an appropriate value for this cell based on the table context") | D25: Tickets | F25: 350 | G25: =SUM(SUMIFS(GL!$C:$C,GL!$G:$G,CONCATENATE(A25,"*"),GL!$F:$F,"Refund"),SUMIFS(GL!$C:$C,GL!$G:$G,CONCATENATE(A25,"*"),GL!$F:$F,"Expense")) -> #N/A | H25: =SUMIFS(GL!$C:$C,GL!$G:$G,CONCATENATE($A25,"*"),GL!$F:$F,"Income") -> #N/A | I25: Pay what you want donation based
A26: T1020 | B26: NCTC (20 kids) | C26: =IFERROR(__xludf.DUMMYFUNCTION("AI(""Fill an appropriate value for this cell based on the table context"")"),"=AI(""Fill an appropriate value for this cell based on the table context"")") -> =AI("Fill an appropriate value for this cell based on the table context") | D26: Playbills (Jan Show) | E26: -100 | G26: =SUM(SUMIFS(GL!$C:$C,GL!$G:$G,CONCATENATE(A26,"*"),GL!$F:$F,"Refund"),SUMIFS(GL!$C:$C,GL!$G:$G,CONCATENATE(A26,"*"),GL!$F:$F,"Expense")) -> #N/A | H26: =SUMIFS(GL!$C:$C,GL!$G:$G,CONCATENATE($A26,"*"),GL!$F:$F,"Income") -> #N/A
A27: T1021 | B27: NCTC (20 kids) | C27: =IFERROR(__xludf.DUMMYFUNCTION("AI(""Fill an appropriate value for this cell based on the table context"")"),"=AI(""Fill an appropriate value for this cell based on the table context"")") -> =AI("Fill an appropriate value for this cell based on the table context") | D27: Concessions (Jan Show) | E27: -100 | F27: 150 | G27: =SUM(SUMIFS(GL!$C:$C,GL!$G:$G,CONCATENATE(A27,"*"),GL!$F:$F,"Refund"),SUMIFS(GL!$C:$C,GL!$G:$G,CONCATENATE(A27,"*"),GL!$F:$F,"Expense")) -> #N/A | H27: =SUMIFS(GL!$C:$C,GL!$G:$G,CONCATENATE($A27,"*"),GL!$F:$F,"Income") -> #N/A
A28: T1022 | B28: NCTC (20 kids) | C28: =IFERROR(__xludf.DUMMYFUNCTION("AI(""Fill an appropriate value for this cell based on the table context"")"),"=AI(""Fill an appropriate value for this cell based on the table context"")") -> =AI("Fill an appropriate value for this cell based on the table context") | D28: Roses (Jan Show) | E28: -100 | F28: 200 | G28: =SUM(SUMIFS(GL!$C:$C,GL!$G:$G,CONCATENATE(A28,"*"),GL!$F:$F,"Refund"),SUMIFS(GL!$C:$C,GL!$G:$G,CONCATENATE(A28,"*"),GL!$F:$F,"Expense")) -> #N/A | H28: =SUMIFS(GL!$C:$C,GL!$G:$G,CONCATENATE($A28,"*"),GL!$F:$F,"Income") -> #N/A
B29: Totals | C29: =IFERROR(__xludf.DUMMYFUNCTION("AI(""Fill an appropriate value for this cell based on the table context"")"),"=AI(""Fill an appropriate value for this cell based on the table context"")") -> =AI("Fill an appropriate value for this cell based on the table context") | E29: =SUM(E15:E28) -> -3485 | F29: =SUM(F15:F28) -> 1770 | G29: =SUM(G15:G28) -> #N/A | H29: =SUM(H15:H28) -> #N/A
B30: Net | C30: =IFERROR(__xludf.DUMMYFUNCTION("AI(""Fill an appropriate value for this cell based on the table context"")"),"=AI(""Fill an appropriate value for this cell based on the table context"")") -> =AI("Fill an appropriate value for this cell based on the table context") | F30: =F29+E29 -> -1715 | H30: =H29+G29 -> #N/A
C31: =IFERROR(__xludf.DUMMYFUNCTION("AI(""Fill an appropriate value for this cell based on the table context"")"),"=AI(""Fill an appropriate value for this cell based on the table context"")") -> =AI("Fill an appropriate value for this cell based on the table context")
A32: T1023 | B32: Fall Revue #1 | C32: Villans | D32: Dues | F32: 1150 | G32: =SUM(SUMIFS(GL!$C:$C,GL!$G:$G,CONCATENATE(A32,"*"),GL!$F:$F,"Refund"),SUMIFS(GL!$C:$C,GL!$G:$G,CONCATENATE(A32,"*"),GL!$F:$F,"Expense")) -> #N/A | H32: =SUMIFS(GL!$C:$C,GL!$G:$G,CONCATENATE($A32,"*"),GL!$F:$F,"Income") -> #N/A | I32: Dues: 23 X $50 per student
A33: T1024 | B33: Fall Revue #1 | C33: Villans | D33: T-shirts | E33: -360 | G33: =SUM(SUMIFS(GL!$C:$C,GL!$G:$G,CONCATENATE(A33,"*"),GL!$F:$F,"Refund"),SUMIFS(GL!$C:$C,GL!$G:$G,CONCATENATE(A33,"*"),GL!$F:$F,"Expense")) -> #N/A | H33: =SUMIFS(GL!$C:$C,GL!$G:$G,CONCATENATE($A33,"*"),GL!$F:$F,"Income") -> #N/A | I33: INCLUDED IN DUES:23 X $12 per shirt
A34: T1025 | B34: Fall Revue #1 | C34: Villans | D34: Set/prop/costume | E34: 0 | G34: =SUM(SUMIFS(GL!$C:$C,GL!$G:$G,CONCATENATE(A34,"*"),GL!$F:$F,"Refund"),SUMIFS(GL!$C:$C,GL!$G:$G,CONCATENATE(A34,"*"),GL!$F:$F,"Expense")) -> #N/A | H34: =SUMIFS(GL!$C:$C,GL!$G:$G,CONCATENATE($A34,"*"),GL!$F:$F,"Income") -> #N/A
A35: T1026 | B35: Fall Revue #1 | C35: Villans | D35: Marketing | E35: -100 | G35: =SUM(SUMIFS(GL!$C:$C,GL!$G:$G,CONCATENATE(A35,"*"),GL!$F:$F,"Refund"),SUMIFS(GL!$C:$C,GL!$G:$G,CONCATENATE(A35,"*"),GL!$F:$F,"Expense")) -> #N/A | H35: =SUMIFS(GL!$C:$C,GL!$G:$G,CONCATENATE($A35,"*"),GL!$F:$F,"Income") -> #N/A
A36: T1027 | B36: Fall Revue #1 | C36: Villans | D36: Concessions | E36: -100 | F36: 150 | G36: =SUM(SUMIFS(GL!$C:$C,GL!$G:$G,CONCATENATE(A36,"*"),GL!$F:$F,"Refund"),SUMIFS(GL!$C:$C,GL!$G:$G,CONCATENATE(A36,"*"),GL!$F:$F,"Expense")) -> #N/A | H36: =SUMIFS(GL!$C:$C,GL!$G:$G,CONCATENATE($A36,"*"),GL!$F:$F,"Income") -> #N/A
A37: T1028 | B37: Fall Revue #1 | C37: Villans | D37: Flowers | E37: -100 | F37: 200 | G37: =SUM(SUMIFS(GL!$C:$C,GL!$G:$G,CONCATENATE(A37,"*"),GL!$F:$F,"Refund"),SUMIFS(GL!$C:$C,GL!$G:$G,CONCATENATE(A37,"*"),GL!$F:$F,"Expense")) -> #N/A | H37: =SUMIFS(GL!$C:$C,GL!$G:$G,CONCATENATE($A37,"*"),GL!$F:$F,"Income") -> #N/A
A38: T1029 | B38: Fall Revue #1 | C38: Villans | D38: Scholarship | E38: -50 | G38: =SUM(SUMIFS(GL!$C:$C,GL!$G:$G,CONCATENATE(A38,"*"),GL!$F:$F,"Refund"),SUMIFS(GL!$C:$C,GL!$G:$G,CONCATENATE(A38,"*"),GL!$F:$F,"Expense")) -> #N/A | H38: =SUMIFS(GL!$C:$C,GL!$G:$G,CONCATENATE($A38,"*"),GL!$F:$F,"Income") -> #N/A
A39: T1030 | B39: Fall Revue #1 | C39: Villans | D39: Meals | E39: 0 | F39: 0 | G39: =SUM(SUMIFS(GL!$C:$C,GL!$G:$G,CONCATENATE(A39,"*"),GL!$F:$F,"Refund"),SUMIFS(GL!$C:$C,GL!$G:$G,CONCATENATE(A39,"*"),GL!$F:$F,"Expense")) -> #N/A | H39: =SUMIFS(GL!$C:$C,GL!$G:$G,CONCATENATE($A39,"*"),GL!$F:$F,"Income") -> #N/A
A40: T1031 | B40: Fall Revue #1 | C40: Villans | D40: Ticket Sales | F40: 1000 | G40: =SUM(SUMIFS(GL!$C:$C,GL!$G:$G,CONCATENATE(A40,"*"),GL!$F:$F,"Refund"),SUMIFS(GL!$C:$C,GL!$G:$G,CONCATENATE(A40,"*"),GL!$F:$F,"Expense")) -> #N/A | H40: =SUMIFS(GL!$C:$C,GL!$G:$G,CONCATENATE($A40,"*"),GL!$F:$F,"Income") -> #N/A | I40: 100 tickets X $10/ticket
B41: Totals | C41: Villans | E41: =SUM(E32:E40) -> -710 | F41: =SUM(F32:F40) -> 2500 | G41: =SUM(G32:G40) -> #N/A | H41: =SUM(H32:H40) -> #N/A
B42: Net | C42: Villans | F42: =F41+E41 -> 1790 | H42: =H41+G41 -> #N/A | I42: 1 scholarship
C43: =IFERROR(__xludf.DUMMYFUNCTION("AI(""Fill an appropriate value for this cell based on the table context"")"),"=AI(""Fill an appropriate value for this cell based on the table context"")") -> =AI("Fill an appropriate value for this cell based on the table context")
A44: T1032 | B44: Fall Play | C44: The Great Gatsby | D44: Licensing | G44: =SUM(SUMIFS(GL!$C:$C,GL!$G:$G,CONCATENATE(A44,"*"),GL!$F:$F,"Refund"),SUMIFS(GL!$C:$C,GL!$G:$G,CONCATENATE(A44,"*"),GL!$F:$F,"Expense")) -> #N/A | H44: =SUMIFS(GL!$C:$C,GL!$G:$G,CONCATENATE($A44,"*"),GL!$F:$F,"Income") -> #N/A | I44: free
A45: T1033 | B45: Fall Play | C45: The Great Gatsby | D45: Dues | F45: 4900 | G45: =SUM(SUMIFS(GL!$C:$C,GL!$G:$G,CONCATENATE(A45,"*"),GL!$F:$F,"Refund"),SUMIFS(GL!$C:$C,GL!$G:$G,CONCATENATE(A45,"*"),GL!$F:$F,"Expense")) -> #N/A | H45: =SUMIFS(GL!$C:$C,GL!$G:$G,CONCATENATE($A45,"*"),GL!$F:$F,"Income") -> #N/A | I45: 34 @ $100 and 20 @ $75
A46: T1034 | B46: Fall Play | C46: The Great Gatsby | D46: Scholarship | E46: -300 | G46: =SUM(SUMIFS(GL!$C:$C,GL!$G:$G,CONCATENATE(A46,"*"),GL!$F:$F,"Refund"),SUMIFS(GL!$C:$C,GL!$G:$G,CONCATENATE(A46,"*"),GL!$F:$F,"Expense")) -> #N/A | H46: =SUMIFS(GL!$C:$C,GL!$G:$G,CONCATENATE($A46,"*"),GL!$F:$F,"Income") -> #N/A | I46: 3 @ $100
A47: T1035 | B47: Fall Play | C47: The Great Gatsby | D47: T-shirts | E47: -720 | F47: 90 | G47: =SUM(SUMIFS(GL!$C:$C,GL!$G:$G,CONCATENATE(A47,"*"),GL!$F:$F,"Refund"),SUMIFS(GL!$C:$C,GL!$G:$G,CONCATENATE(A47,"*"),GL!$F:$F,"Expense")) -> #N/A | H47: =SUMIFS(GL!$C:$C,GL!$G:$G,CONCATENATE($A47,"*"),GL!$F:$F,"Income") -> #N/A | I47: INCLUDED IN DUES: 54 X $12 per shirt
A48: T1036 | B48: Fall Play | C48: The Great Gatsby | D48: Meals | E48: -2600 | G48: =SUM(SUMIFS(GL!$C:$C,GL!$G:$G,CONCATENATE(A48,"*"),GL!$F:$F,"Refund"),SUMIFS(GL!$C:$C,GL!$G:$G,CONCATENATE(A48,"*"),GL!$F:$F,"Expense")) -> #N/A | H48: =SUMIFS(GL!$C:$C,GL!$G:$G,CONCATENATE($A48,"*"),GL!$F:$F,"Income") -> #N/A | I48: $12/student for 4 meals *(if no meal discount)
A49: T1037 | B49: Fall Play | C49: The Great Gatsby | D49: Set Build | E49: -1100 | G49: =SUM(SUMIFS(GL!$C:$C,GL!$G:$G,CONCATENATE(A49,"*"),GL!$F:$F,"Refund"),SUMIFS(GL!$C:$C,GL!$G:$G,CONCATENATE(A49,"*"),GL!$F:$F,"Expense")) -> #N/A | H49: =SUMIFS(GL!$C:$C,GL!$G:$G,CONCATENATE($A49,"*"),GL!$F:$F,"Income") -> #N/A
A50: T1038 | B50: Fall Play | C50: The Great Gatsby | D50: Props | E50: -430 | G50: =SUM(SUMIFS(GL!$C:$C,GL!$G:$G,CONCATENATE(A50,"*"),GL!$F:$F,"Refund"),SUMIFS(GL!$C:$C,GL!$G:$G,CONCATENATE(A50,"*"),GL!$F:$F,"Expense")) -> #N/A | H50: =SUMIFS(GL!$C:$C,GL!$G:$G,CONCATENATE($A50,"*"),GL!$F:$F,"Income") -> #N/A
A51: T1039 | B51: Fall Play | C51: The Great Gatsby | D51: Costumes | E51: -1000 | G51: =SUM(SUMIFS(GL!$C:$C,GL!$G:$G,CONCATENATE(A51,"*"),GL!$F:$F,"Refund"),SUMIFS(GL!$C:$C,GL!$G:$G,CONCATENATE(A51,"*"),GL!$F:$F,"Expense")) -> #N/A | H51: =SUMIFS(GL!$C:$C,GL!$G:$G,CONCATENATE($A51,"*"),GL!$F:$F,"Income") -> #N/A
A52: T1040 | B52: Fall Play | C52: The Great Gatsby | D52: Concessions | E52: -300 | F52: 600 | G52: =SUM(SUMIFS(GL!$C:$C,GL!$G:$G,CONCATENATE(A52,"*"),GL!$F:$F,"Refund"),SUMIFS(GL!$C:$C,GL!$G:$G,CONCATENATE(A52,"*"),GL!$F:$F,"Expense")) -> #N/A | H52: =SUMIFS(GL!$C:$C,GL!$G:$G,CONCATENATE($A52,"*"),GL!$F:$F,"Income") -> #N/A
A53: T1041 | B53: Fall Play | C53: The Great Gatsby | D53: Playbills | E53: -500 | G53: =SUM(SUMIFS(GL!$C:$C,GL!$G:$G,CONCATENATE(A53,"*"),GL!$F:$F,"Refund"),SUMIFS(GL!$C:$C,GL!$G:$G,CONCATENATE(A53,"*"),GL!$F:$F,"Expense")) -> #N/A | H53: =SUMIFS(GL!$C:$C,GL!$G:$G,CONCATENATE($A53,"*"),GL!$F:$F,"Income") -> #N/A
A54: T1042 | B54: Fall Play | C54: The Great Gatsby | D54: Playbill ads | F54: 500 | G54: =SUM(SUMIFS(GL!$C:$C,GL!$G:$G,CONCATENATE(A54,"*"),GL!$F:$F,"Refund"),SUMIFS(GL!$C:$C,GL!$G:$G,CONCATENATE(A54,"*"),GL!$F:$F,"Expense")) -> #N/A | H54: =SUMIFS(GL!$C:$C,GL!$G:$G,CONCATENATE($A54,"*"),GL!$F:$F,"Income") -> #N/A
A55: T1043 | B55: Fall Play | C55: The Great Gatsby | D55: Ticket Sales | F55: 5000 | G55: =SUM(SUMIFS(GL!$C:$C,GL!$G:$G,CONCATENATE(A55,"*"),GL!$F:$F,"Refund"),SUMIFS(GL!$C:$C,GL!$G:$G,CONCATENATE(A55,"*"),GL!$F:$F,"Expense")) -> #N/A | H55: =SUMIFS(GL!$C:$C,GL!$G:$G,CONCATENATE($A55,"*"),GL!$F:$F,"Income") -> #N/A | I55: approx $12.50/ticket x 125 tickets/show x 4 shows
A56: T1044 | B56: Fall Play | C56: The Great Gatsby | D56: Flowers | E56: -200 | F56: 400 | G56: =SUM(SUMIFS(GL!$C:$C,GL!$G:$G,CONCATENATE(A56,"*"),GL!$F:$F,"Refund"),SUMIFS(GL!$C:$C,GL!$G:$G,CONCATENATE(A56,"*"),GL!$F:$F,"Expense")) -> #N/A | H56: =SUMIFS(GL!$C:$C,GL!$G:$G,CONCATENATE($A56,"*"),GL!$F:$F,"Income") -> #N/A
A57: T1045 | B57: Fall Play | C57: The Great Gatsby | D57: Marketing | E57: -600 | G57: =SUM(SUMIFS(GL!$C:$C,GL!$G:$G,CONCATENATE(A57,"*"),GL!$F:$F,"Refund"),SUMIFS(GL!$C:$C,GL!$G:$G,CONCATENATE(A57,"*"),GL!$F:$F,"Expense")) -> #N/A | H57: =SUMIFS(GL!$C:$C,GL!$G:$G,CONCATENATE($A57,"*"),GL!$F:$F,"Income") -> #N/A | I57: banners, FB advertising
A58: T1046 | B58: Fall Play | C58: The Great Gatsby | D58: Misc | E58: -300 | G58: =SUM(SUMIFS(GL!$C:$C,GL!$G:$G,CONCATENATE(A58,"*"),GL!$F:$F,"Refund"),SUMIFS(GL!$C:$C,GL!$G:$G,CONCATENATE(A58,"*"),GL!$F:$F,"Expense")) -> #N/A | H58: =SUMIFS(GL!$C:$C,GL!$G:$G,CONCATENATE($A58,"*"),GL!$F:$F,"Income") -> #N/A
A59: T1047 | B59: Fall Play | C59: The Great Gatsby | D59: Snacks | E59: -100 | G59: =SUM(SUMIFS(GL!$C:$C,GL!$G:$G,CONCATENATE(A59,"*"),GL!$F:$F,"Refund"),SUMIFS(GL!$C:$C,GL!$G:$G,CONCATENATE(A59,"*"),GL!$F:$F,"Expense")) -> #N/A | H59: =SUMIFS(GL!$C:$C,GL!$G:$G,CONCATENATE($A59,"*"),GL!$F:$F,"Income") -> #N/A | I59: Cake too
B60: Totals | C60: MidSummer Nights Dream | E60: =SUM(E44:E59) -> -8150 | F60: =SUM(F44:F59) -> 11490 | G60: =SUM(G44:G59) -> #N/A | H60: =SUM(H44:H59) -> #N/A
B61: Net | C61: MidSummer Nights Dream | F61: =F60+E60 -> 3340 | H61: =H60+G60 -> #N/A | I61: 2 scholarships
C62: =IFERROR(__xludf.DUMMYFUNCTION("AI(""Fill an appropriate value for this cell based on the table context"")"),"=AI(""Fill an appropriate value for this cell based on the table context"")") -> =AI("Fill an appropriate value for this cell based on the table context")
A63: T1048 | B63: Fall Revue #2 | C63: R&R | D63: Dues | F63: 1150 | G63: =SUM(SUMIFS(GL!$C:$C,GL!$G:$G,CONCATENATE(A63,"*"),GL!$F:$F,"Refund"),SUMIFS(GL!$C:$C,GL!$G:$G,CONCATENATE(A63,"*"),GL!$F:$F,"Expense")) -> #N/A | H63: =SUMIFS(GL!$C:$C,GL!$G:$G,CONCATENATE($A63,"*"),GL!$F:$F,"Income") -> #N/A | I63: Dues: 23 X $50 per student
A64: T1049 | B64: Fall Revue #3 | C64: R&R | D64: T-shirts | E64: -360 | G64: =SUM(SUMIFS(GL!$C:$C,GL!$G:$G,CONCATENATE(A64,"*"),GL!$F:$F,"Refund"),SUMIFS(GL!$C:$C,GL!$G:$G,CONCATENATE(A64,"*"),GL!$F:$F,"Expense")) -> #N/A | H64: =SUMIFS(GL!$C:$C,GL!$G:$G,CONCATENATE($A64,"*"),GL!$F:$F,"Income") -> #N/A | I64: INCLUDED IN DUES: 30 X $12 per shirt
A65: T1050 | B65: Fall Revue #4 | C65: R&R | D65: Set/prop/costume | G65: =SUM(SUMIFS(GL!$C:$C,GL!$G:$G,CONCATENATE(A65,"*"),GL!$F:$F,"Refund"),SUMIFS(GL!$C:$C,GL!$G:$G,CONCATENATE(A65,"*"),GL!$F:$F,"Expense")) -> #N/A | H65: =SUMIFS(GL!$C:$C,GL!$G:$G,CONCATENATE($A65,"*"),GL!$F:$F,"Income") -> #N/A
A66: T1051 | B66: Fall Revue #5 | C66: R&R | D66: Misc | E66: -100 | G66: =SUM(SUMIFS(GL!$C:$C,GL!$G:$G,CONCATENATE(A66,"*"),GL!$F:$F,"Refund"),SUMIFS(GL!$C:$C,GL!$G:$G,CONCATENATE(A66,"*"),GL!$F:$F,"Expense")) -> #N/A | H66: =SUMIFS(GL!$C:$C,GL!$G:$G,CONCATENATE($A66,"*"),GL!$F:$F,"Income") -> #N/A
A67: T1052 | B67: Fall Revue #6 | C67: R&R | D67: Concessions | E67: -100 | F67: 150 | G67: =SUM(SUMIFS(GL!$C:$C,GL!$G:$G,CONCATENATE(A67,"*"),GL!$F:$F,"Refund"),SUMIFS(GL!$C:$C,GL!$G:$G,CONCATENATE(A67,"*"),GL!$F:$F,"Expense")) -> #N/A | H67: =SUMIFS(GL!$C:$C,GL!$G:$G,CONCATENATE($A67,"*"),GL!$F:$F,"Income") -> #N/A
A68: T1053 | B68: Fall Revue #7 | C68: R&R | D68: Flowers | E68: -100 | F68: 200 | G68: =SUM(SUMIFS(GL!$C:$C,GL!$G:$G,CONCATENATE(A68,"*"),GL!$F:$F,"Refund"),SUMIFS(GL!$C:$C,GL!$G:$G,CONCATENATE(A68,"*"),GL!$F:$F,"Expense")) -> #N/A | H68: =SUMIFS(GL!$C:$C,GL!$G:$G,CONCATENATE($A68,"*"),GL!$F:$F,"Income") -> #N/A
A69: T1054 | B69: Fall Revue #8 | C69: R&R | D69: Scholarship | E69: -50 | G69: =SUM(SUMIFS(GL!$C:$C,GL!$G:$G,CONCATENATE(A69,"*"),GL!$F:$F,"Refund"),SUMIFS(GL!$C:$C,GL!$G:$G,CONCATENATE(A69,"*"),GL!$F:$F,"Expense")) -> #N/A | H69: =SUMIFS(GL!$C:$C,GL!$G:$G,CONCATENATE($A69,"*"),GL!$F:$F,"Income") -> #N/A
A70: T1055 | B70: Fall Revue #9 | C70: R&R | D70: Meals | E70: 0 | F70: 0 | G70: =SUM(SUMIFS(GL!$C:$C,GL!$G:$G,CONCATENATE(A70,"*"),GL!$F:$F,"Refund"),SUMIFS(GL!$C:$C,GL!$G:$G,CONCATENATE(A70,"*"),GL!$F:$F,"Expense")) -> #N/A | H70: =SUMIFS(GL!$C:$C,GL!$G:$G,CONCATENATE($A70,"*"),GL!$F:$F,"Income") -> #N/A
A71: T1056 | B71: Fall Revue #10 | C71: R&R | D71: Ticket Sales | F71: 1000 | G71: =SUM(SUMIFS(GL!$C:$C,GL!$G:$G,CONCATENATE(A71,"*"),GL!$F:$F,"Refund"),SUMIFS(GL!$C:$C,GL!$G:$G,CONCATENATE(A71,"*"),GL!$F:$F,"Expense")) -> #N/A | H71: =SUMIFS(GL!$C:$C,GL!$G:$G,CONCATENATE($A71,"*"),GL!$F:$F,"Income") -> #N/A | I71: 100 tickets X $10/ticket
B72: Totals | C72: R&R | E72: =SUM(E63:E71) -> -710 | F72: =SUM(F63:F71) -> 2500 | G72: =SUM(G63:G71) -> #N/A | H72: =SUM(H63:H71) -> #N/A
B73: Net | C73: R&R | F73: =F72+E72 -> 1790 | H73: =H72+G72 -> #N/A | I73: 1 scholarship
C74: =IFERROR(__xludf.DUMMYFUNCTION("AI(""Fill an appropriate value for this cell based on the table context"")"),"=AI(""Fill an appropriate value for this cell based on the table context"")") -> =AI("Fill an appropriate value for this cell based on the table context")
A75: T1057 | B75: Spring Musical | C75: Hunchback of Notre Dame | D75: Licensing | G75: =SUM(SUMIFS(GL!$C:$C,GL!$G:$G,CONCATENATE(A75,"*"),GL!$F:$F,"Refund"),SUMIFS(GL!$C:$C,GL!$G:$G,CONCATENATE(A75,"*"),GL!$F:$F,"Expense")) -> #N/A | H75: =SUMIFS(GL!$C:$C,GL!$G:$G,CONCATENATE($A75,"*"),GL!$F:$F,"Income") -> #N/A | I75: $3196.97 +$400- paid during 24-25 expendatures. Required for blumey budget
A76: T1058 | B76: Spring Musical | C76: Hunchback of Notre Dame | D76: Dues | F76: 7375 | G76: =SUM(SUMIFS(GL!$C:$C,GL!$G:$G,CONCATENATE(A76,"*"),GL!$F:$F,"Refund"),SUMIFS(GL!$C:$C,GL!$G:$G,CONCATENATE(A76,"*"),GL!$F:$F,"Expense")) -> #N/A | H76: =SUMIFS(GL!$C:$C,GL!$G:$G,CONCATENATE($A76,"*"),GL!$F:$F,"Income") -> #N/A | I76: 35 @ $125 and 30 @ $100
A77: T1059 | B77: Spring Musical | C77: Hunchback of Notre Dame | D77: Scholarship | E77: -375 | G77: =SUM(SUMIFS(GL!$C:$C,GL!$G:$G,CONCATENATE(A77,"*"),GL!$F:$F,"Refund"),SUMIFS(GL!$C:$C,GL!$G:$G,CONCATENATE(A77,"*"),GL!$F:$F,"Expense")) -> #N/A | H77: =SUMIFS(GL!$C:$C,GL!$G:$G,CONCATENATE($A77,"*"),GL!$F:$F,"Income") -> #N/A | I77: 3 @ $125
A78: T1060 | B78: Spring Musical | C78: Hunchback of Notre Dame | D78: T-shirts | E78: -1200 | F78: 525 | G78: =SUM(SUMIFS(GL!$C:$C,GL!$G:$G,CONCATENATE(A78,"*"),GL!$F:$F,"Refund"),SUMIFS(GL!$C:$C,GL!$G:$G,CONCATENATE(A78,"*"),GL!$F:$F,"Expense")) -> #N/A | H78: =SUMIFS(GL!$C:$C,GL!$G:$G,CONCATENATE($A78,"*"),GL!$F:$F,"Income") -> #N/A | I78: INCLUDED IN DUES: 65 X $12 per shirt
A79: T1061 | B79: Spring Musical | C79: Hunchback of Notre Dame | D79: Meals | E79: -3120 | G79: =SUM(SUMIFS(GL!$C:$C,GL!$G:$G,CONCATENATE(A79,"*"),GL!$F:$F,"Refund"),SUMIFS(GL!$C:$C,GL!$G:$G,CONCATENATE(A79,"*"),GL!$F:$F,"Expense")) -> #N/A | H79: =SUMIFS(GL!$C:$C,GL!$G:$G,CONCATENATE($A79,"*"),GL!$F:$F,"Income") -> #N/A | I79: $12/student for 4 meals *(if no meal discount)
A80: T1062 | B80: Spring Musical | C80: Hunchback of Notre Dame | D80: Set Build | E80: -2500 | G80: =SUM(SUMIFS(GL!$C:$C,GL!$G:$G,CONCATENATE(A80,"*"),GL!$F:$F,"Refund"),SUMIFS(GL!$C:$C,GL!$G:$G,CONCATENATE(A80,"*"),GL!$F:$F,"Expense")) -> #N/A | H80: =SUMIFS(GL!$C:$C,GL!$G:$G,CONCATENATE($A80,"*"),GL!$F:$F,"Income") -> #N/A | I80: includes screen/images
A81: T1063 | B81: Spring Musical | C81: Hunchback of Notre Dame | D81: Props | E81: -500 | G81: =SUM(SUMIFS(GL!$C:$C,GL!$G:$G,CONCATENATE(A81,"*"),GL!$F:$F,"Refund"),SUMIFS(GL!$C:$C,GL!$G:$G,CONCATENATE(A81,"*"),GL!$F:$F,"Expense")) -> #N/A | H81: =SUMIFS(GL!$C:$C,GL!$G:$G,CONCATENATE($A81,"*"),GL!$F:$F,"Income") -> #N/A
A82: T1064 | B82: Spring Musical | C82: Hunchback of Notre Dame | D82: Costumes | E82: -3000 | G82: =SUM(SUMIFS(GL!$C:$C,GL!$G:$G,CONCATENATE(A82,"*"),GL!$F:$F,"Refund"),SUMIFS(GL!$C:$C,GL!$G:$G,CONCATENATE(A82,"*"),GL!$F:$F,"Expense")) -> #N/A | H82: =SUMIFS(GL!$C:$C,GL!$G:$G,CONCATENATE($A82,"*"),GL!$F:$F,"Income") -> #N/A
A83: T1065 | B83: Spring Musical | C83: Hunchback of Notre Dame | D83: Concessions | E83: -300 | F83: 600 | G83: =SUM(SUMIFS(GL!$C:$C,GL!$G:$G,CONCATENATE(A83,"*"),GL!$F:$F,"Refund"),SUMIFS(GL!$C:$C,GL!$G:$G,CONCATENATE(A83,"*"),GL!$F:$F,"Expense")) -> #N/A | H83: =SUMIFS(GL!$C:$C,GL!$G:$G,CONCATENATE($A83,"*"),GL!$F:$F,"Income") -> #N/A
A84: T1066 | B84: Spring Musical | C84: Hunchback of Notre Dame | D84: Playbills | E84: -1000 | G84: =SUM(SUMIFS(GL!$C:$C,GL!$G:$G,CONCATENATE(A84,"*"),GL!$F:$F,"Refund"),SUMIFS(GL!$C:$C,GL!$G:$G,CONCATENATE(A84,"*"),GL!$F:$F,"Expense")) -> #N/A | H84: =SUMIFS(GL!$C:$C,GL!$G:$G,CONCATENATE($A84,"*"),GL!$F:$F,"Income") -> #N/A
A85: T1067 | B85: Spring Musical | C85: Hunchback of Notre Dame | D85: Playbill ads | F85: 800 | G85: =SUM(SUMIFS(GL!$C:$C,GL!$G:$G,CONCATENATE(A85,"*"),GL!$F:$F,"Refund"),SUMIFS(GL!$C:$C,GL!$G:$G,CONCATENATE(A85,"*"),GL!$F:$F,"Expense")) -> #N/A | H85: =SUMIFS(GL!$C:$C,GL!$G:$G,CONCATENATE($A85,"*"),GL!$F:$F,"Income") -> #N/A
A86: T1068 | B86: Spring Musical | C86: Hunchback of Notre Dame | D86: Ticket Sales | F86: 10000 | G86: =SUM(SUMIFS(GL!$C:$C,GL!$G:$G,CONCATENATE(A86,"*"),GL!$F:$F,"Refund"),SUMIFS(GL!$C:$C,GL!$G:$G,CONCATENATE(A86,"*"),GL!$F:$F,"Expense")) -> #N/A | H86: =SUMIFS(GL!$C:$C,GL!$G:$G,CONCATENATE($A86,"*"),GL!$F:$F,"Income") -> #N/A | I86: approx $12.50/ticket x 250 tickets/show x 4 shows
A87: T1069 | B87: Spring Musical | C87: Hunchback of Notre Dame | D87: Flowers | E87: -200 | F87: 400 | G87: =SUM(SUMIFS(GL!$C:$C,GL!$G:$G,CONCATENATE(A87,"*"),GL!$F:$F,"Refund"),SUMIFS(GL!$C:$C,GL!$G:$G,CONCATENATE(A87,"*"),GL!$F:$F,"Expense")) -> #N/A | H87: =SUMIFS(GL!$C:$C,GL!$G:$G,CONCATENATE($A87,"*"),GL!$F:$F,"Income") -> #N/A
A88: T1070 | B88: Spring Musical | C88: Hunchback of Notre Dame | D88: Marketing | E88: -900 | G88: =SUM(SUMIFS(GL!$C:$C,GL!$G:$G,CONCATENATE(A88,"*"),GL!$F:$F,"Refund"),SUMIFS(GL!$C:$C,GL!$G:$G,CONCATENATE(A88,"*"),GL!$F:$F,"Expense")) -> #N/A | H88: =SUMIFS(GL!$C:$C,GL!$G:$G,CONCATENATE($A88,"*"),GL!$F:$F,"Income") -> #N/A
A89: T1071 | B89: Spring Musical | C89: Hunchback of Notre Dame | D89: Misc | E89: 0 | G89: =SUM(SUMIFS(GL!$C:$C,GL!$G:$G,CONCATENATE(A89,"*"),GL!$F:$F,"Refund"),SUMIFS(GL!$C:$C,GL!$G:$G,CONCATENATE(A89,"*"),GL!$F:$F,"Expense")) -> #N/A | H89: =SUMIFS(GL!$C:$C,GL!$G:$G,CONCATENATE($A89,"*"),GL!$F:$F,"Income") -> #N/A
A90: T1072 | B90: Spring Musical | C90: Hunchback of Notre Dame | D90: Snacks | G90: =SUM(SUMIFS(GL!$C:$C,GL!$G:$G,CONCATENATE(A90,"*"),GL!$F:$F,"Refund"),SUMIFS(GL!$C:$C,GL!$G:$G,CONCATENATE(A90,"*"),GL!$F:$F,"Expense")) -> #N/A | H90: =SUMIFS(GL!$C:$C,GL!$G:$G,CONCATENATE($A90,"*"),GL!$F:$F,"Income") -> #N/A
A91: T1073 | B91: Spring Musical | C91: Hunchback of Notre Dame | D91: Music Assistance | E91: -800 | G91: =SUM(SUMIFS(GL!$C:$C,GL!$G:$G,CONCATENATE(A91,"*"),GL!$F:$F,"Refund"),SUMIFS(GL!$C:$C,GL!$G:$G,CONCATENATE(A91,"*"),GL!$F:$F,"Expense")) -> #N/A | H91: =SUMIFS(GL!$C:$C,GL!$G:$G,CONCATENATE($A91,"*"),GL!$F:$F,"Income") -> #N/A
B92: Totals | C92: Mama Mia | E92: =SUM(E75:E91) -> -13895 | F92: =SUM(F75:F91) -> 19700 | G92: =SUM(G75:G91) -> #N/A | H92: =SUM(H75:H91) -> #N/A
B93: Net | C93: Mama Mia | F93: =F92+E92 -> 5805 | H93: =H92+G92 -> #N/A | I93: 1 scholarship
C94: =IFERROR(__xludf.DUMMYFUNCTION("AI(""Fill an appropriate value for this cell based on the table context"")"),"=AI(""Fill an appropriate value for this cell based on the table context"")") -> =AI("Fill an appropriate value for this cell based on the table context")
A95: T1074 | B95: Spring Revue #3 | C95: Dreams vs Nightmares | D95: Dues | F95: 1150 | G95: =SUM(SUMIFS(GL!$C:$C,GL!$G:$G,CONCATENATE(A95,"*"),GL!$F:$F,"Refund"),SUMIFS(GL!$C:$C,GL!$G:$G,CONCATENATE(A95,"*"),GL!$F:$F,"Expense")) -> #N/A | H95: =SUMIFS(GL!$C:$C,GL!$G:$G,CONCATENATE($A95,"*"),GL!$F:$F,"Income") -> #N/A | I95: Dues: 23 X $50 per student
A96: T1075 | B96: Spring Revue #3 | C96: Dreams vs Nightmares | D96: T-shirts | E96: -360 | G96: =SUM(SUMIFS(GL!$C:$C,GL!$G:$G,CONCATENATE(A96,"*"),GL!$F:$F,"Refund"),SUMIFS(GL!$C:$C,GL!$G:$G,CONCATENATE(A96,"*"),GL!$F:$F,"Expense")) -> #N/A | H96: =SUMIFS(GL!$C:$C,GL!$G:$G,CONCATENATE($A96,"*"),GL!$F:$F,"Income") -> #N/A | I96: INCLUDED IN DUES: 30 X $12 per shirt
A97: T1076 | B97: Spring Revue #3 | C97: Dreams vs Nightmares | D97: Set/prop/costume | G97: =SUM(SUMIFS(GL!$C:$C,GL!$G:$G,CONCATENATE(A97,"*"),GL!$F:$F,"Refund"),SUMIFS(GL!$C:$C,GL!$G:$G,CONCATENATE(A97,"*"),GL!$F:$F,"Expense")) -> #N/A | H97: =SUMIFS(GL!$C:$C,GL!$G:$G,CONCATENATE($A97,"*"),GL!$F:$F,"Income") -> #N/A
A98: T1077 | B98: Spring Revue #3 | C98: Dreams vs Nightmares | D98: Misc | E98: -100 | G98: =SUM(SUMIFS(GL!$C:$C,GL!$G:$G,CONCATENATE(A98,"*"),GL!$F:$F,"Refund"),SUMIFS(GL!$C:$C,GL!$G:$G,CONCATENATE(A98,"*"),GL!$F:$F,"Expense")) -> #N/A | H98: =SUMIFS(GL!$C:$C,GL!$G:$G,CONCATENATE($A98,"*"),GL!$F:$F,"Income") -> #N/A
A99: T1078 | B99: Spring Revue #3 | C99: Dreams vs Nightmares | D99: Concessions | E99: -100 | F99: 150 | G99: =SUM(SUMIFS(GL!$C:$C,GL!$G:$G,CONCATENATE(A99,"*"),GL!$F:$F,"Refund"),SUMIFS(GL!$C:$C,GL!$G:$G,CONCATENATE(A99,"*"),GL!$F:$F,"Expense")) -> #N/A | H99: =SUMIFS(GL!$C:$C,GL!$G:$G,CONCATENATE($A99,"*"),GL!$F:$F,"Income") -> #N/A
A100: T1079 | B100: Spring Revue #3 | C100: Dreams vs Nightmares | D100: Flowers | E100: -100 | F100: 200 | G100: =SUM(SUMIFS(GL!$C:$C,GL!$G:$G,CONCATENATE(A100,"*"),GL!$F:$F,"Refund"),SUMIFS(GL!$C:$C,GL!$G:$G,CONCATENATE(A100,"*"),GL!$F:$F,"Expense")) -> #N/A | H100: =SUMIFS(GL!$C:$C,GL!$G:$G,CONCATENATE($A100,"*"),GL!$F:$F,"Income") -> #N/A
...
